fastpsl-0.1.0.dist-info/METADATA
fastpsl-0.1.0.dist-info/WHEEL
fastpsl-0.1.0.dist-info/licenses/LICENSE
fastpsl/__init__.py
fastpsl/__init__.pyi
fastpsl/fastpsl.pypy310-pp73-ppc_64-linux-gnu.so
fastpsl/py.typed
fastpsl-0.1.0.dist-info/RECORD
