Metadata-Version: 2.4
Name: fastpsl
Version: 0.1.0
Classifier: Programming Language :: Rust
Classifier: Programming Language :: Python :: Implementation :: CPython
Classifier: Programming Language :: Python :: Implementation :: PyPy
License-File: LICENSE
Maintainer-email: ssrtw <pixar9899@gmail.com>
Requires-Python: >=3.8
Project-URL: homepage, https://github.com/ssrtw/fastpsl/
